hierarqcal/__init__.py
hierarqcal/core.py
hierarqcal/utils.py
hierarqcal/cirq/__init__.py
hierarqcal/cirq/cirq_circuits.py
hierarqcal/cirq/cirq_helper.py
hierarqcal/cirq/tf_helper.py
hierarqcal/pennylane/__init__.py
hierarqcal/pennylane/pennylane_circuits.py
hierarqcal/pennylane/pennylane_helper.py
hierarqcal/qiskit/__init__.py
hierarqcal/qiskit/qiskit_circuits.py
hierarqcal/qiskit/qiskit_helper.py
hierarqcal-0.5.0.dist-info/LICENSE.txt
hierarqcal-0.5.0.dist-info/METADATA
hierarqcal-0.5.0.dist-info/WHEEL
hierarqcal-0.5.0.dist-info/top_level.txt
hierarqcal-0.5.0.dist-info/RECORD
