Metadata-Version: 2.1
Name: hierarqcal
Version: 0.5.0
License-File: LICENSE.txt
Requires-Dist: requests
Requires-Dist: numpy
Requires-Dist: sympy
Requires-Dist: matplotlib
Requires-Dist: ipykernel
Requires-Dist: jupyterlab
Requires-Dist: importlib-metadata ; python_version < "3.8"
Provides-Extra: cirq
Requires-Dist: cirq ; extra == 'cirq'
Provides-Extra: pennylane
Requires-Dist: pennylane ; extra == 'pennylane'
Provides-Extra: qiskit
Requires-Dist: qiskit[visualization] ; extra == 'qiskit'
